jaraco/env.py
jaraco.env-1.0.0.dist-info/LICENSE
jaraco.env-1.0.0.dist-info/METADATA
jaraco.env-1.0.0.dist-info/WHEEL
jaraco.env-1.0.0.dist-info/top_level.txt
jaraco.env-1.0.0.dist-info/RECORD
