Metadata-Version: 2.1
Name: jaraco.env
Version: 1.0.0
Summary: Facilities for environment variables
Home-page: https://github.com/jaraco/jaraco.env
Author: Jason R. Coombs
Author-email: jaraco@jaraco.com
Classifier: Development Status :: 5 - Production/Stable
Classifier: Intended Audience :: Developers
Classifier: License :: OSI Approved :: MIT License
Classifier: Programming Language :: Python :: 3
Classifier: Programming Language :: Python :: 3 :: Only
Requires-Python: >=3.7
Provides-Extra: testing
Provides-Extra: docs
License-File: LICENSE
